pyutube/__init__.py
pyutube/__main__.py
pyutube/cli.py
pyutube/utils.py
pyutube/handlers/PlaylistHandler.py
pyutube/handlers/URLHandler.py
pyutube/handlers/__init__.py
pyutube/services/AudioService.py
pyutube/services/DownloadService.py
pyutube/services/FileService.py
pyutube/services/VideoService.py
pyutube/services/__init__.py
pyutube/tests/__init__.py
pyutube/tests/test_utils.py
pyutube-1.5.0.dist-info/LICENSE
pyutube-1.5.0.dist-info/METADATA
pyutube-1.5.0.dist-info/WHEEL
pyutube-1.5.0.dist-info/entry_points.txt
pyutube-1.5.0.dist-info/top_level.txt
pyutube-1.5.0.dist-info/RECORD
