Metadata-Version: 2.2
Name: pyutube
Version: 1.5.0
Summary: Awesome CLI to download YouTube videos (as video or audio)/shorts/playlists from the terminal
Author: Ebraheem Alhetari
Author-email: hetari4all@gmail.com
License: MIT
Project-URL: Author, https://github.com/Hetari
Project-URL: Homepage, https://github.com/Hetari/pyutube
Project-URL: Bug Tracker, https://github.com/Hetari/pyutube/issues
Project-URL: Source Code, https://github.com/Hetari/pyutube
Project-URL: Documentation, https://github.com/Hetari/pyutube
Keywords: youtube,download,cli,pyutube,pytubefix,pytube,youtube-dl
Platform: Linux
Platform: Windows
Platform: MacOS
Classifier: License :: OSI Approved :: MIT License
Classifier: Operating System :: OS Independent
Classifier: Programming Language :: Python :: 3
Requires-Python: >=3.6
License-File: LICENSE
Requires-Dist: pytubefix
Requires-Dist: inquirer
Requires-Dist: yaspin
Requires-Dist: typer
Requires-Dist: requests
Requires-Dist: rich
Requires-Dist: termcolor
Requires-Dist: moviepy
Requires-Dist: setuptools
Dynamic: author
Dynamic: author-email
Dynamic: classifier
Dynamic: description
Dynamic: description-content-type
Dynamic: keywords
Dynamic: license
Dynamic: platform
Dynamic: project-url
Dynamic: requires-dist
Dynamic: requires-python
Dynamic: summary
